socket_throttle/__init__.py
socket_throttle/core.py
socket_throttle/files.py
socket_throttle/leaky_bucket.py
socket_throttle/sockets.py
socket_throttle-0.2.1.dist-info/METADATA
socket_throttle-0.2.1.dist-info/WHEEL
socket_throttle-0.2.1.dist-info/RECORD
